{"peanutbutter": [639.0, "no_entity"], "sugar": [387.0, "no_entity"], "toast": [267.0, "no_entity"], "water": [0.0, "no_entity"], "oats": [371.0, "no_entity"], "linsen": [341.0, "no_entity"], "kichererbsen dose": [120.0, "no_entity"], "gehackte tomaten": [24.0, "no_entity"], "zwiebel": [28.0, "no_entity"], "kartoffel": [71.0, "no_entity"], "\u00f6l": [828.0, "no_entity"], "zucker": [400.0, "no_entity"], "k\u00fcrbiskerne": [567.0, "no_entity"], "haferflocken": [371.0, "no_entity"], "banane": [89.0, "no_entity"], "erbsenleberwurst": [220.0, "no_entity"], "roggenvollkornbrot": [214.0, "no_entity"], "erdn\u00fcsse": [619.0, "no_entity"], "kuerbiskerne": [570.0, "no_entity"], "erdbeeren tiefgefroren": [29.0, "no_entity"], "balsamicocreme": [187.0, "no_entity"], "rucola": [25.0, "no_entity"], "tomate": [21.0, "no_entity"], "oliven\u00f6l": [822.0, "no_entity"], "streuk\u00e4se vegan myway": [302.0, "no_entity"], "reis": [351.0, "no_entity"], "kiwi": [62.0, "no_entity"], "sonnenblumenkerne": [629.0, "no_entity"], "gurke": [12.0, "no_entity"], "kebap vegan planted": [213.0, "no_entity"], "kidneybohnen dose abgetropft": [107.0, "no_entity"], "mais dose": [83.0, "no_entity"], "raps\u00f6l": [819.0, "no_entity"], "spezi dose": [124.2, "entity", 333.0], "lauchzwiebel": [42.0, "no_entity"], "gouda": [364.0, "no_entity"], "gnocci": [150.0, "no_entity"], "staudensellerie": [15.0, "no_entity"], "so\u00dfe": [234.0, "entity", 2.0], "neuuu": [234.0, "entity", 2.0], "dackel": [234.0, "entity", 3.0], "zucchini": [69.0, "no_entity"], "bulgur": [345.0, "no_entity"], "passierte tomate 500g": [135.0, "entity", 500.0], "gem\u00fcse tiefgefroren": [30.0, "no_entity"], "zwiebel klein": [12.0, "entity", 42.0], "champignon eingelegt": [19.0, "no_entity"], "balance frischk\u00e4se": [167.0, "no_entity"], "milch 3,5%": [64.0, "no_entity"], "gekochte nudeln": [137.0, "no_entity"], "weizentoast scheibe": [95.0, "entity", 38.0], "geramont": [320.0, "no_entity"], "avocado": [160.0, "no_entity"], "saaa": [3.0, "entity", 2.0], "paprika": [38.0, "no_entity"], "vanille joghurt": [100.0, "no_entity"], "nektarine": [55.0, "no_entity"], "nimm2 soft": [18.0, "entity", 4.7], "gekochte kartoffel": [69.0, "no_entity"], "saure gurken": [11.0, "no_entity"], "dill": [3.0, "no_entity"], "eistee pfanner pfirsich": [26.0, "no_entity"], "feuerdrachen": [435.0, "no_entity"], "mozzarella": [238.0, "no_entity"], "wasabi crunch": [461.0, "no_entity"], "kesselchips": [492.0, "no_entity"], "weizenbrot": [247.0, "no_entity"], "nocciolata": [544.0, "no_entity"], "hafermilch": [53.0, "no_entity"], "ritter sport halbbitter": [534.0, "no_entity"], "orangensaft": [42.0, "no_entity"], "mandeln": [609.0, "no_entity"], "brokkoli": [35.0, "no_entity"], "like beef style": [104.0, "no_entity"], "m\u00f6hre": [39.0, "no_entity"], "sesam": [600.0, "no_entity"], "sojasauce": [77.0, "no_entity"], "zitronensaft": [26.0, "no_entity"], "sweet chili sauce": [178.0, "no_entity"], "gekochter reis": [120.0, "no_entity"], "eistee 4bro peach": [29.0, "no_entity"], "chio red paprika": [530.0, "no_entity"], "hagelslag": [446.0, "no_entity"], "quark": [72.0, "no_entity"], "sojamilch": [35.0, "no_entity"], "reibekuchen ": [175.0, "no_entity"], "blaubeeren tiefgefroren": [51.0, "no_entity"], "stadionwurst vegan": [201.0, "no_entity"], "kr\u00e4uterbaguette rewe vegan": [558.25, "entity", 175.0], "ei": [86.0, "entity", 55.0], "k\u00f6rnerbr\u00f6tchen": [174.0, "entity", 65.0], "rohkakao": [621.0, "no_entity"], "mini fr\u00fchlingsrollen": [234.0, "no_entity"]}